{"chunk_definitions":[{"chunk_id":"cdt5ox8z0kg3u","chunk_label":"unnamed-chunk-2","document_id":"9643902D","expansion_state":0,"options":{"engine":"r","fig.align":"center","fig.cap":"Lienzo con características por defecto","fig.height":3,"fig.width":4,"label":"unnamed-chunk-43"},"row":72,"row_count":1,"visible":true},{"chunk_id":"crr7v1x00a177","chunk_label":"unnamed-chunk-3","document_id":"9643902D","expansion_state":0,"options":{"engine":"r","fig.align":"center","fig.cap":"Reduciendo los márgenes del lienzo","fig.height":3,"fig.width":4,"label":"unnamed-chunk-44"},"row":86,"row_count":1,"visible":true},{"chunk_id":"ccedsmqvx5tul","chunk_label":"unnamed-chunk-4","document_id":"9643902D","expansion_state":0,"options":{"engine":"r","fig.align":"center","fig.cap":"Lienzo con dos gráficos de igual tamaño","fig.height":3,"fig.width":6,"label":"unnamed-chunk-45"},"row":113,"row_count":1,"visible":true},{"chunk_id":"cbk1fsb38vwl5","chunk_label":"unnamed-chunk-5","document_id":"9643902D","expansion_state":0,"options":{"engine":"r","fig.align":"center","fig.cap":"Lienzo con dos gráficos de tamaño variable","fig.height":3,"fig.width":6,"label":"unnamed-chunk-46"},"row":136,"row_count":1,"visible":true},{"chunk_id":"cxzevasxj4son","chunk_label":"unnamed-chunk-6","document_id":"9643902D","expansion_state":0,"options":{"engine":"r","fig.align":"center","fig.cap":"Lienzo con dos gráficos de tamaño variable 2","fig.height":3.500000000000000,"fig.width":6,"label":"unnamed-chunk-47"},"row":161,"row_count":1,"visible":true},{"chunk_id":"c3uht54vloauo","chunk_label":"unnamed-chunk-7","document_id":"9643902D","expansion_state":0,"options":{"engine":"r","fig.align":"center","fig.cap":"Tipos de símbolos gráficos desplegados","fig.height":4,"fig.width":4,"label":"unnamed-chunk-48"},"row":186,"row_count":1,"visible":true},{"chunk_id":"ccy7ynagoewjb","chunk_label":"unnamed-chunk-8","document_id":"9643902D","expansion_state":0,"options":{"engine":"r","fig.align":"center","fig.cap":"Tipos de líneas desplegadas en gráficos","fig.height":3,"fig.width":4,"label":"unnamed-chunk-49"},"row":198,"row_count":1,"visible":true},{"chunk_id":"c8vmqjn3173tk","chunk_label":"unnamed-chunk-9","document_id":"9643902D","expansion_state":0,"options":{"engine":"r","fig.align":"center","fig.cap":"Anatomía de un gráfico","fig.height":4,"fig.width":5,"label":"unnamed-chunk-50"},"row":226,"row_count":1,"visible":true}],"doc_write_time":1477715020}